[{"id":"inject1","type":"inject","z":"flow1","name":"Número","props":[{"p":"payload"}],"repeat":"","once":false,"onceDelay":0.1,"topic":"","payload":"5","payloadType":"num","x":140,"y":100,"wires":[["switch1"]]},{"id":"switch1","type":"switch","z":"flow1","name":"Mayor que 10","property":"payload","propertyType":"msg","rules":[{"t":"gt","v":"10","vt":"num"}],"checkall":"true","repair":false,"outputs":1,"x":330,"y":100,"wires":[["debug1"]]},{"id":"debug1","type":"debug","z":"flow1","name":"Es mayor","active":true,"tosidebar":true,"console":false,"tostatus":false,"complete":"payload","targetType":"msg","x":500,"y":100,"wires":[]}]

